dtail/__init__.py
dtail-1.0.0.data/scripts/dtail
dtail-1.0.0.dist-info/LICENSE
dtail-1.0.0.dist-info/METADATA
dtail-1.0.0.dist-info/WHEEL
dtail-1.0.0.dist-info/top_level.txt
dtail-1.0.0.dist-info/RECORD
